{
    "title": "Caps Lock Vim Movements (rev 2)",
    "rules": [
        {
            "description": "CAPS › ESC, CAPS+H/J/K/L › ←↓↑→, CAPS+D/U › PG↓↑, CAPS+=/- › VOL±, CAPS+0 › MUTE, CAPS+CMD+=/- › BRIGHT±, CAPS+,/.// › PREV/NEXT/PLAY",
            "manipulators": [
                {
                    "conditions": [
                        {
                            "name": "caps_lock pressed",
                            "type": "variable_if",
                            "value": 1
                        }
                    ],
                    "from": {
                        "key_code": "j",
                        "modifiers": {
                            "optional": [
                                "any"
                            ]
                        }
                    },
                    "to": [
                        {
                            "key_code": "down_arrow"
                        }
                    ],
                    "type": "basic"
                },
                {
                    "conditions": [
                        {
                            "name": "caps_lock pressed",
                            "type": "variable_if",
                            "value": 1
                        }
                    ],
                    "from": {
                        "key_code": "k",
                        "modifiers": {
                            "optional": [
                                "any"
                            ]
                        }
                    },
                    "to": [
                        {
                            "key_code": "up_arrow"
                        }
                    ],
                    "type": "basic"
                },
                {
                    "conditions": [
                        {
                            "name": "caps_lock pressed",
                            "type": "variable_if",
                            "value": 1
                        }
                    ],
                    "from": {
                        "key_code": "h",
                        "modifiers": {
                            "optional": [
                                "any"
                            ]
                        }
                    },
                    "to": [
                        {
                            "key_code": "left_arrow"
                        }
                    ],
                    "type": "basic"
                },
                {
                    "conditions": [
                        {
                            "name": "caps_lock pressed",
                            "type": "variable_if",
                            "value": 1
                        }
                    ],
                    "from": {
                        "key_code": "l",
                        "modifiers": {
                            "optional": [
                                "any"
                            ]
                        }
                    },
                    "to": [
                        {
                            "key_code": "right_arrow"
                        }
                    ],
                    "type": "basic"
                },
                {
                    "conditions": [
                        {
                            "name": "caps_lock pressed",
                            "type": "variable_if",
                            "value": 1
                        }
                    ],
                    "from": {
                        "key_code": "d",
                        "modifiers": {
                            "optional": [
                                "any"
                            ]
                        }
                    },
                    "to": [
                        {
                            "key_code": "page_down"
                        }
                    ],
                    "type": "basic"
                },
                {
                    "conditions": [
                        {
                            "name": "caps_lock pressed",
                            "type": "variable_if",
                            "value": 1
                        }
                    ],
                    "from": {
                        "key_code": "u",
                        "modifiers": {
                            "optional": [
                                "any"
                            ]
                        }
                    },
                    "to": [
                        {
                            "key_code": "page_up"
                        }
                    ],
                    "type": "basic"
                },
                {
                    "conditions": [
                        {
                            "name": "caps_lock pressed",
                            "type": "variable_if",
                            "value": 1
                        }
                    ],
                    "from": {
                        "key_code": "equal_sign",
                        "modifiers": {
                            "mandatory": [
                                "command"
                            ],
                            "optional": [
                                "any"
                            ]
                        }
                    },
                    "to": [
                        {
                            "key_code": "display_brightness_increment"
                        }
                    ],
                    "type": "basic"
                },
                {
                    "conditions": [
                        {
                            "name": "caps_lock pressed",
                            "type": "variable_if",
                            "value": 1
                        }
                    ],
                    "from": {
                        "key_code": "hyphen",
                        "modifiers": {
                            "mandatory": [
                                "command"
                            ],
                            "optional": [
                                "any"
                            ]
                        }
                    },
                    "to": [
                        {
                            "key_code": "display_brightness_decrement"
                        }
                    ],
                    "type": "basic"
                },
                {
                    "conditions": [
                        {
                            "name": "caps_lock pressed",
                            "type": "variable_if",
                            "value": 1
                        }
                    ],
                    "from": {
                        "key_code": "equal_sign",
                        "modifiers": {
                            "optional": [
                                "any"
                            ]
                        }
                    },
                    "to": [
                        {
                            "key_code": "volume_increment"
                        }
                    ],
                    "type": "basic"
                },
                {
                    "conditions": [
                        {
                            "name": "caps_lock pressed",
                            "type": "variable_if",
                            "value": 1
                        }
                    ],
                    "from": {
                        "key_code": "hyphen",
                        "modifiers": {
                            "optional": [
                                "any"
                            ]
                        }
                    },
                    "to": [
                        {
                            "key_code": "volume_decrement"
                        }
                    ],
                    "type": "basic"
                },
                {
                    "conditions": [
                        {
                            "name": "caps_lock pressed",
                            "type": "variable_if",
                            "value": 1
                        }
                    ],
                    "from": {
                        "key_code": "0",
                        "modifiers": {
                            "optional": [
                                "any"
                            ]
                        }
                    },
                    "to": [
                        {
                            "key_code": "mute"
                        }
                    ],
                    "type": "basic"
                },
                {
                    "conditions": [
                        {
                            "name": "caps_lock pressed",
                            "type": "variable_if",
                            "value": 1
                        }
                    ],
                    "from": {
                        "key_code": "comma",
                        "modifiers": {
                            "optional": [
                                "any"
                            ]
                        }
                    },
                    "to": [
                        {
                            "key_code": "rewind"
                        }
                    ],
                    "type": "basic"
                },
                {
                    "conditions": [
                        {
                            "name": "caps_lock pressed",
                            "type": "variable_if",
                            "value": 1
                        }
                    ],
                    "from": {
                        "key_code": "period",
                        "modifiers": {
                            "optional": [
                                "any"
                            ]
                        }
                    },
                    "to": [
                        {
                            "key_code": "fastforward"
                        }
                    ],
                    "type": "basic"
                },
                {
                    "conditions": [
                        {
                            "name": "caps_lock pressed",
                            "type": "variable_if",
                            "value": 1
                        }
                    ],
                    "from": {
                        "key_code": "slash",
                        "modifiers": {
                            "optional": [
                                "any"
                            ]
                        }
                    },
                    "to": [
                        {
                            "key_code": "play_or_pause"
                        }
                    ],
                    "type": "basic"
                },
                {
                    "from": {
                        "key_code": "caps_lock",
                        "modifiers": {
                            "optional": [
                                "any"
                            ]
                        }
                    },
                    "to": [
                        {
                            "set_variable": {
                                "name": "caps_lock pressed",
                                "value": 1
                            }
                        }
                    ],
                    "to_after_key_up": [
                        {
                            "set_variable": {
                                "name": "caps_lock pressed",
                                "value": 0
                            }
                        }
                    ],
                    "to_if_alone": [
                        {
                            "key_code": "escape"
                        }
                    ],
                    "type": "basic"
                }
            ]
        },
        {
            "description": "CAPS+↩︎ › CAPS",
            "manipulators": [
                {
                    "conditions": [
                        {
                            "name": "caps_lock pressed",
                            "type": "variable_if",
                            "value": 1
                        }
                    ],
                    "from": {
                        "key_code": "return_or_enter",
                        "modifiers": {
                            "optional": [
                                "any"
                            ]
                        }
                    },
                    "to": [
                        {
                            "key_code": "caps_lock"
                        }
                    ],
                    "type": "basic"
                }
            ]
        },
        {
            "description": "CAPS+A › CAPS",
            "manipulators": [
                {
                    "conditions": [
                        {
                            "name": "caps_lock pressed",
                            "type": "variable_if",
                            "value": 1
                        }
                    ],
                    "from": {
                        "key_code": "a",
                        "modifiers": {
                            "optional": [
                                "any"
                            ]
                        }
                    },
                    "to": [
                        {
                            "key_code": "caps_lock"
                        }
                    ],
                    "type": "basic"
                }
            ]
        }
    ]
}
